dbcv/Cache_warming.npy
dbcv/__init__.py
dbcv/_dbcv_float32np.py
dbcv/_dbcv_float32p.py
dbcv/_dbcv_float64np.py
dbcv/_dbcv_float64p.py
dbcv/main.py
dbcv/setup_script.py
dbcv-1.0.5.dist-info/LICENSE
dbcv-1.0.5.dist-info/METADATA
dbcv-1.0.5.dist-info/WHEEL
dbcv-1.0.5.dist-info/entry_points.txt
dbcv-1.0.5.dist-info/top_level.txt
dbcv-1.0.5.dist-info/RECORD
