Metadata-Version: 2.1
Name: dbcv
Version: 1.0.5
Summary: This library allows you to compute the Density-Based Clustering Validation metric quickly and with low memory consumption
Home-page: https://github.com/boyfws/DBCV
Author: db.boy
Author-email: minkin.d.d@gmail.com
Classifier: Programming Language :: Python :: 3.12
Classifier: License :: OSI Approved :: MIT License
Classifier: Operating System :: OS Independent
Requires-Python: >=3.5
License-File: LICENSE
Requires-Dist: numba ==0.60.0
Requires-Dist: numpy <=1.26.4,>=1.19.5
